lesya/__init__.py
lesya/language/__init__.py
lesya/language/case_helpers.py
lesya/language/name_case.py
lesya/language/name_constants.py
lesya/language/nc_core.py
lesya/language/data/__init__.py
lesya/language/data/family-names.pkl
lesya-0.0.8.dist-info/LICENSE
lesya-0.0.8.dist-info/METADATA
lesya-0.0.8.dist-info/WHEEL
lesya-0.0.8.dist-info/top_level.txt
lesya-0.0.8.dist-info/RECORD
