Metadata-Version: 2.1
Name: lesya
Version: 0.0.8
Summary: Python package to form Ukrainian names cases : 'Леся Українка' -- 'Лесі Українки' , 'Лесі Українці', 'Лесею Українкою' ... etc.
Author: Dmytro Ustynov
Author-email: Dmytro Ustynov <ustynov.dev@gmail.com>
License: Copyright (c) 2024 Dmytro Ustynov
Project-URL: Homepage, https://github.com/ustynov-py-dev/lesya.git
Project-URL: Issues, https://github.com/ustynov-py-dev/lesya/issues
Classifier: Programming Language :: Python :: 3
Classifier: License :: OSI Approved :: MIT License
Classifier: Operating System :: OS Independent
Requires-Python: >=3.8
License-File: LICENSE
